odoo/addons/website_media_size/README.rst
odoo/addons/website_media_size/__init__.py
odoo/addons/website_media_size/__manifest__.py
odoo/addons/website_media_size/static/description/screenshot.png
odoo/addons/website_media_size/static/src/css/website_media_size.css
odoo/addons/website_media_size/static/src/js/website_media_size.js
odoo/addons/website_media_size/static/src/xml/website_media_size.xml
odoo/addons/website_media_size/templates/assets.xml
odoo11_addon_website_media_size-11.0.1.0.0.dist-info/DESCRIPTION.rst
odoo11_addon_website_media_size-11.0.1.0.0.dist-info/METADATA
odoo11_addon_website_media_size-11.0.1.0.0.dist-info/RECORD
odoo11_addon_website_media_size-11.0.1.0.0.dist-info/WHEEL
odoo11_addon_website_media_size-11.0.1.0.0.dist-info/metadata.json
odoo11_addon_website_media_size-11.0.1.0.0.dist-info/top_level.txt
